repo2string/__init__.py
repo2string/__main__.py
repo2string/cli.py
repo2string/scan.py
repo2string/ui.html
repo2string/ui_server.py
repo2string-0.4.2.dist-info/METADATA
repo2string-0.4.2.dist-info/WHEEL
repo2string-0.4.2.dist-info/entry_points.txt
repo2string-0.4.2.dist-info/top_level.txt
repo2string-0.4.2.dist-info/RECORD
