Metadata-Version: 2.2
Name: repo2string
Version: 0.4.2
Summary: Copy any repository into the clipboard. And get the token count.
Author-email: Maciej Szulc <szulcmaciej1@gmail.com>
License: MIT
Project-URL: Homepage, https://github.com/szulcmaciej/repo2string
Project-URL: Bug Tracker, https://github.com/szulcmaciej/repo2string/issues
Keywords: llm,chatgpt,repository,context,tokens,clipboard
Classifier: Development Status :: 4 - Beta
Classifier: Environment :: Console
Classifier: Intended Audience :: Developers
Classifier: License :: OSI Approved :: MIT License
Classifier: Operating System :: OS Independent
Classifier: Programming Language :: Python :: 3
Classifier: Programming Language :: Python :: 3.8
Classifier: Programming Language :: Python :: 3.9
Classifier: Programming Language :: Python :: 3.10
Classifier: Programming Language :: Python :: 3.11
Classifier: Topic :: Software Development :: Libraries :: Python Modules
Classifier: Topic :: Text Processing :: General
Requires-Python: >=3.8
Requires-Dist: pyperclip
Requires-Dist: pathspec
Requires-Dist: tiktoken
Requires-Dist: Flask
Provides-Extra: test
Requires-Dist: pytest>=7.0; extra == "test"
Requires-Dist: pytest-cov>=4.0; extra == "test"
Requires-Dist: ruff>=0.1.0; extra == "test"
Requires-Dist: pre-commit<4.0.0,>=3.5.0; extra == "test"
